Metadata-Version: 2.1
Name: naukri-Jobs-Scraper
Version: 1.0.3
Summary: A python library to scrape naukri job details
Home-page: UNKNOWN
Author: DataKund
Author-email: datakund@gmail.com
License: Apache License 2.0
Keywords: naukri,python,bot_studio,automation,search,scraper,scrape,job,location,experince,salary,role,industrytype
Platform: UNKNOWN
License-File: LICENSE
